sqlcli/__init__.py
sqlcli/commandanalyze.py
sqlcli/datawrapper.py
sqlcli/hbasewrapper.py
sqlcli/hdfswrapper.py
sqlcli/kafkawrapper.py
sqlcli/main.py
sqlcli/newkafkawrapper.py
sqlcli/rabbitmqwrapper.py
sqlcli/rediswrapper.py
sqlcli/sqlcli.py
sqlcli/sqlcliexception.py
sqlcli/sqlclijdbcapi.py
sqlcli/sqlclijobmanager.py
sqlcli/sqlclimeta.py
sqlcli/sqlcliodbc.cp38-win_amd64.pyd
sqlcli/sqlcliodbc.py
sqlcli/sqlcliremoteserver.py
sqlcli/sqlclitransactionmanager.py
sqlcli/sqlexecute.py
sqlcli/sqloption.py
sqlcli/sqlparse.py
sqlcli/sshwrapper.py
sqlcli/testwrapper.py
sqlcli/conf/sqlcli.ini
sqlcli/jlib/README
sqlcli/odbc/CMakeLists.txt
sqlcli/odbc/ceoApiTypes.c
sqlcli/odbc/ceoConnection.c
sqlcli/odbc/ceoCursor.c
sqlcli/odbc/ceoDbType.c
sqlcli/odbc/ceoError.c
sqlcli/odbc/ceoModule.c
sqlcli/odbc/ceoModule.h
sqlcli/odbc/ceoTransform.c
sqlcli/odbc/ceoUtils.c
sqlcli/odbc/ceoVar.c
sqlcli/profile/default
robotslacker_sqlcli-0.2.65.dist-info/LICENSE.txt
robotslacker_sqlcli-0.2.65.dist-info/METADATA
robotslacker_sqlcli-0.2.65.dist-info/WHEEL
robotslacker_sqlcli-0.2.65.dist-info/entry_points.txt
robotslacker_sqlcli-0.2.65.dist-info/top_level.txt
robotslacker_sqlcli-0.2.65.dist-info/RECORD
