Metadata-Version: 2.1
Name: robotslacker-sqlcli
Version: 0.2.65
Summary: SQL Command test tool, use JDBC/ODBC
Home-page: https://github.com/robotslacker/sqlcli
Author: RobotSlacker
Author-email: 184902652@qq.com
License: UNKNOWN
Keywords: sql command test tool
Platform: any
Requires-Python: >=3.6
Requires-Dist: JPype1
Requires-Dist: setproctitle
Requires-Dist: pathlib
Requires-Dist: urllib3
Requires-Dist: pyparsing
Requires-Dist: click
Requires-Dist: prompt-toolkit
Requires-Dist: fs
Requires-Dist: hdfs
Requires-Dist: wget
Requires-Dist: httptools
Requires-Dist: pika
Requires-Dist: paramiko
Requires-Dist: requests
Requires-Dist: websockets
Requires-Dist: pydantic
Requires-Dist: uvicorn[standard]
Requires-Dist: fastapi
Requires-Dist: hbase-thrift
Requires-Dist: thrift
Requires-Dist: redis
Requires-Dist: redis-py-cluster
